[
  {
    "semestre": "1 Semestre",
    "ramos": [
      { "nombre": "Anatomía general", "estado": "desbloqueado", "abre": ["Fisiología humana", "Anatomía del sistema visual"] },
      { "nombre": "Biología Humana e Histología", "estado": "desbloqueado", "abre": ["Fisiología humana", "Anatomía del sistema visual"] },
      { "nombre": "Química general y orgánica", "estado": "desbloqueado", "abre": ["Bioquímica"] },
      { "nombre": "Matemáticas", "estado": "desbloqueado", "abre": ["Física general"] },
      { "nombre": "Introducción a la tecnología médica en oftalmología", "estado": "desbloqueado", "abre": ["Interacción humana y sociocultural"] },
      { "nombre": "Expresión oral y escrita", "estado": "desbloqueado", "abre": ["Interacción humana y sociocultural"] },
      { "nombre": "Taller de inglés", "estado": "desbloqueado", "abre": ["Inglés general"] }
    ]
  },
  {
    "semestre": "2 Semestre",
    "ramos": [
      { "nombre": "Fisiología humana", "estado": "bloqueado", "abre": ["Fisiopatología humana", "Enfermería básica"] },
      { "nombre": "Anatomía del sistema visual", "estado": "bloqueado", "abre": [] },
      { "nombre": "Bioquímica", "estado": "bloqueado", "abre": ["Farmacología general"] },
      { "nombre": "Física general", "estado": "bloqueado", "abre": ["Física óptica"] },
      { "nombre": "Inglés general", "estado": "bloqueado", "abre": ["Inglés técnico"] },
      { "nombre": "Interacción humana y sociocultural", "estado": "bloqueado", "abre": ["Psicología de la salud"] }
    ]
  },
  {
    "semestre": "3 Semestre",
    "ramos": [
      { "nombre": "Fisiopatología humana", "estado": "bloqueado", "abre": ["Microbiología e inmunología", "Semiología del sistema visual"] },
      { "nombre": "Enfermería básica", "estado": "bloqueado", "abre": ["Farmacología ocular"] },
      { "nombre": "Farmacología general", "estado": "bloqueado", "abre": ["Farmacología ocular"] },
      { "nombre": "Física óptica", "estado": "bloqueado", "abre": ["Fundamentos de la oftalmología"] },
      { "nombre": "Psicología de la salud", "estado": "bloqueado", "abre": ["Salud pública"] },
      { "nombre": "Inglés técnico", "estado": "bloqueado", "abre": [] }
    ]
  },
  {
    "semestre": "4 Semestre",
    "ramos": [
      { "nombre": "Microbiología e inmunología", "estado": "bloqueado", "abre": [] },
      { "nombre": "Semiología del sistema visual", "estado": "bloqueado", "abre": ["Fundamentos del glaucoma", "Fundamentos del estrabismo"] },
      { "nombre": "Farmacología ocular", "estado": "bloqueado", "abre": ["Fundamentos del glaucoma"] },
      { "nombre": "Fundamentos de la oftalmología", "estado": "bloqueado", "abre": ["Fundamentos del estrabismo", "Fundamentos del campo visual"] },
      { "nombre": "Salud pública", "estado": "bloqueado", "abre": ["Gestión y liderazgo", "Bioestadística"] },
      { "nombre": "Electivo de formación general", "estado": "bloqueado", "abre": [] }
    ]
  },
  {
    "semestre": "5 Semestre",
    "ramos": [
      { "nombre": "Fundamentos del glaucoma", "estado": "bloqueado", "abre": ["Glaucoma y campo visual", "Optometría 1"] },
      { "nombre": "Fundamentos del estrabismo", "estado": "bloqueado", "abre": ["Técnicas ortópticas y pleópticas", "Optometría 1"] },
      { "nombre": "Fundamentos del campo visual", "estado": "bloqueado", "abre": ["Glaucoma y campo visual"] },
      { "nombre": "Gestión y liderazgo", "estado": "bloqueado", "abre": [] },
      { "nombre": "Bioestadística", "estado": "bloqueado", "abre": ["Metodología de la investigación en oftalmología"] },
      { "nombre": "Bioética", "estado": "bloqueado", "abre": ["Metodología de la investigación en oftalmología"] }
    ]
  },
  {
    "semestre": "6 Semestre",
    "ramos": [
      { "nombre": "Glaucoma y campo visual", "estado": "bloqueado", "abre": ["Neuroftalmología", "Clínica de atención primaria"] },
      { "nombre": "Técnicas ortópticas y pleópticas", "estado": "bloqueado", "abre": ["Neuroftalmología", "Clínica de atención primaria"] },
      { "nombre": "Fisiopatología del polo posterior", "estado": "bloqueado", "abre": ["Imagenología ocular"] },
      { "nombre": "Optometría 1", "estado": "bloqueado", "abre": ["Técnicas de apoyo para cirugía refractiva", "Optometría 2", "Seminario de grado 1", "Clínica de atención primaria"] },
      { "nombre": "Metodología de la investigación en oftalmología", "estado": "bloqueado", "abre": ["Seminario de grado 1"] }
    ]
  },
  {
    "semestre": "7 Semestre",
    "ramos": [
      { "nombre": "Neuroftalmología", "estado": "bloqueado", "abre": [] },
      { "nombre": "Técnicas de apoyo para cirugía refractiva", "estado": "bloqueado", "abre": ["Biometría ocular"] },
      { "nombre": "Imagenología ocular", "estado": "bloqueado", "abre": ["Biometría ocular"] },
      { "nombre": "Optometría 2", "estado": "bloqueado", "abre": ["Clínica de atención primaria optométrica", "Baja visión", "Seminario de grado 2"] },
      { "nombre": "Seminario de grado 1", "estado": "bloqueado", "abre": ["Seminario de grado 2"] },
      { "nombre": "Clínica de atención primaria", "estado": "bloqueado", "abre": ["Análisis clínico integral"] }
    ]
  },
  {
    "semestre": "8 Semestre",
    "ramos": [
      { "nombre": "Análisis clínico integral", "estado": "bloqueado", "abre": ["Clínica médica"] },
      { "nombre": "Biometría ocular", "estado": "bloqueado", "abre": [] },
      { "nombre": "Clínica de atención primaria optométrica", "estado": "bloqueado", "abre": ["Clínica médica", "Gestión y proyecto de intervención comunitaria"] },
      { "nombre": "Baja visión", "estado": "bloqueado", "abre": [] },
      { "nombre": "Seminario de grado 2", "estado": "bloqueado", "abre": ["Electivo de formación profesional 1", "Electivo de formación profesional 2"] }
    ]
  },
  {
    "semestre": "9 Semestre",
    "ramos": [
      { "nombre": "Clínica médica", "estado": "bloqueado", "abre": [] },
      { "nombre": "Gestión y proyecto de intervención comunitaria", "estado": "bloqueado", "abre": [] },
      { "nombre": "Electivo de formación profesional 1", "estado": "bloqueado", "abre": [] },
      { "nombre": "Electivo de formación profesional 2", "estado": "bloqueado", "abre": [] }
    ]
  },
  {
    "semestre": "10 Semestre",
    "ramos": [
      { "nombre": "Actividad de titulación: internado", "estado": "bloqueado", "abre": [] }
    ]
  }
]
